indico_payment_stripe/__init__.py
indico_payment_stripe/blueprint.py
indico_payment_stripe/controllers.py
indico_payment_stripe/plugin.py
indico_payment_stripe/util.py
indico_payment_stripe/static/images/logo.svg
indico_payment_stripe/templates/event_payment_form.html
indico_payment_stripe/templates/transaction_details.html
indico_payment_stripe/translations/messages.pot
indico_plugin_payment_stripe-3.3.dist-info/METADATA
indico_plugin_payment_stripe-3.3.dist-info/WHEEL
indico_plugin_payment_stripe-3.3.dist-info/entry_points.txt
indico_plugin_payment_stripe-3.3.dist-info/RECORD
